package com.clilystudio.netbook.download;

final class c extends Thread
{
  c(a parama)
  {
  }

  // ERROR //
  public final void run()
  {
    // Byte code:
    //   0: aconst_null
    //   1: astore_1
    //   2: new 18	java/io/File
    //   5: dup
    //   6: aload_0
    //   7: getfield 10	com/ushaqi/zhuishushenqi/download/c:a	Lcom/ushaqi/zhuishushenqi/download/a;
    //   10: invokestatic 24	com/ushaqi/zhuishushenqi/download/a:c	(Lcom/ushaqi/zhuishushenqi/download/a;)Ljava/lang/String;
    //   13: invokespecial 27	java/io/File:<init>	(Ljava/lang/String;)V
    //   16: astore_2
    //   17: aload_2
    //   18: invokevirtual 31	java/io/File:exists	()Z
    //   21: ifne +8 -> 29
    //   24: aload_2
    //   25: invokevirtual 34	java/io/File:mkdirs	()Z
    //   28: pop
    //   29: new 36	java/io/FileOutputStream
    //   32: dup
    //   33: new 18	java/io/File
    //   36: dup
    //   37: aload_0
    //   38: getfield 10	com/ushaqi/zhuishushenqi/download/c:a	Lcom/ushaqi/zhuishushenqi/download/a;
    //   41: invokestatic 24	com/ushaqi/zhuishushenqi/download/a:c	(Lcom/ushaqi/zhuishushenqi/download/a;)Ljava/lang/String;
    //   44: aload_0
    //   45: getfield 10	com/ushaqi/zhuishushenqi/download/c:a	Lcom/ushaqi/zhuishushenqi/download/a;
    //   48: invokestatic 39	com/ushaqi/zhuishushenqi/download/a:d	(Lcom/ushaqi/zhuishushenqi/download/a;)Ljava/lang/String;
    //   51: invokespecial 42	java/io/File:<init>	(Ljava/lang/String;Ljava/lang/String;)V
    //   54: invokespecial 45	java/io/FileOutputStream:<init>	(Ljava/io/File;)V
    //   57: astore 4
    //   59: new 47	java/net/URL
    //   62: dup
    //   63: aload_0
    //   64: getfield 10	com/ushaqi/zhuishushenqi/download/c:a	Lcom/ushaqi/zhuishushenqi/download/a;
    //   67: invokestatic 50	com/ushaqi/zhuishushenqi/download/a:e	(Lcom/ushaqi/zhuishushenqi/download/a;)Ljava/lang/String;
    //   70: invokespecial 51	java/net/URL:<init>	(Ljava/lang/String;)V
    //   73: invokevirtual 55	java/net/URL:openConnection	()Ljava/net/URLConnection;
    //   76: checkcast 57	java/net/HttpURLConnection
    //   79: astore 8
    //   81: aload 8
    //   83: invokevirtual 60	java/net/HttpURLConnection:connect	()V
    //   86: aload 8
    //   88: invokevirtual 64	java/net/HttpURLConnection:getContentLength	()I
    //   91: istore 9
    //   93: aload 8
    //   95: invokevirtual 68	java/net/HttpURLConnection:getInputStream	()Ljava/io/InputStream;
    //   98: astore_1
    //   99: sipush 1024
    //   102: newarray byte
    //   104: astore 10
    //   106: iconst_0
    //   107: istore 11
    //   109: aload_1
    //   110: aload 10
    //   112: invokevirtual 74	java/io/InputStream:read	([B)I
    //   115: istore 12
    //   117: iload 12
    //   119: iconst_m1
    //   120: if_icmpeq +39 -> 159
    //   123: iload 11
    //   125: iload 12
    //   127: iadd
    //   128: istore 11
    //   130: aload 4
    //   132: aload 10
    //   134: iconst_0
    //   135: iload 12
    //   137: invokevirtual 78	java/io/FileOutputStream:write	([BII)V
    //   140: iload 11
    //   142: iload 9
    //   144: if_icmpne -35 -> 109
    //   147: aload_0
    //   148: getfield 10	com/ushaqi/zhuishushenqi/download/c:a	Lcom/ushaqi/zhuishushenqi/download/a;
    //   151: invokestatic 82	com/ushaqi/zhuishushenqi/download/a:f	(Lcom/ushaqi/zhuishushenqi/download/a;)Landroid/os/Handler;
    //   154: iconst_1
    //   155: invokevirtual 88	android/os/Handler:sendEmptyMessage	(I)Z
    //   158: pop
    //   159: aload 4
    //   161: invokevirtual 91	java/io/FileOutputStream:close	()V
    //   164: aload_1
    //   165: ifnull +7 -> 172
    //   168: aload_1
    //   169: invokevirtual 92	java/io/InputStream:close	()V
    //   172: return
    //   173: astore 13
    //   175: aload 13
    //   177: invokevirtual 95	java/io/IOException:printStackTrace	()V
    //   180: return
    //   181: astore 6
    //   183: aconst_null
    //   184: astore 4
    //   186: aload 6
    //   188: invokevirtual 95	java/io/IOException:printStackTrace	()V
    //   191: aload 4
    //   193: ifnull +8 -> 201
    //   196: aload 4
    //   198: invokevirtual 91	java/io/FileOutputStream:close	()V
    //   201: aload_1
    //   202: ifnull -30 -> 172
    //   205: aload_1
    //   206: invokevirtual 92	java/io/InputStream:close	()V
    //   209: return
    //   210: astore 7
    //   212: aload 7
    //   214: invokevirtual 95	java/io/IOException:printStackTrace	()V
    //   217: return
    //   218: astore_3
    //   219: aconst_null
    //   220: astore 4
    //   222: aload 4
    //   224: ifnull +8 -> 232
    //   227: aload 4
    //   229: invokevirtual 91	java/io/FileOutputStream:close	()V
    //   232: aload_1
    //   233: ifnull +7 -> 240
    //   236: aload_1
    //   237: invokevirtual 92	java/io/InputStream:close	()V
    //   240: aload_3
    //   241: athrow
    //   242: astore 5
    //   244: aload 5
    //   246: invokevirtual 95	java/io/IOException:printStackTrace	()V
    //   249: goto -9 -> 240
    //   252: astore_3
    //   253: goto -31 -> 222
    //   256: astore 6
    //   258: goto -72 -> 186
    //
    // Exception table:
    //   from	to	target	type
    //   159	164	173	java/io/IOException
    //   168	172	173	java/io/IOException
    //   2	29	181	java/io/IOException
    //   29	59	181	java/io/IOException
    //   196	201	210	java/io/IOException
    //   205	209	210	java/io/IOException
    //   2	29	218	finally
    //   29	59	218	finally
    //   227	232	242	java/io/IOException
    //   236	240	242	java/io/IOException
    //   59	106	252	finally
    //   109	117	252	finally
    //   130	140	252	finally
    //   147	159	252	finally
    //   186	191	252	finally
    //   59	106	256	java/io/IOException
    //   109	117	256	java/io/IOException
    //   130	140	256	java/io/IOException
    //   147	159	256	java/io/IOException
  }
}

/* Location:           E:\Progs\Dev\Android\Decompile\apktool\zssq\zssq-dex2jar.jar
 * Qualified Name:     com.clilystudio.netbook.download.c
 * JD-Core Version:    0.6.0
 */