package android.support.v7.internal.widget;

import android.os.AsyncTask;

final class q extends AsyncTask<Object, Void, Void>
{
  private q(l paraml)
  {
  }

  // ERROR //
  private Void a(Object[] paramArrayOfObject)
  {
    // Byte code:
    //   0: iconst_0
    //   1: istore_2
    //   2: aload_1
    //   3: iconst_0
    //   4: aaload
    //   5: checkcast 28	java/util/List
    //   8: astore_3
    //   9: aload_1
    //   10: iconst_1
    //   11: aaload
    //   12: checkcast 30	java/lang/String
    //   15: astore 4
    //   17: aload_0
    //   18: getfield 11	android/support/v7/internal/widget/q:a	Landroid/support/v7/internal/widget/l;
    //   21: invokestatic 35	android/support/v7/internal/widget/l:a	(Landroid/support/v7/internal/widget/l;)Landroid/content/Context;
    //   24: aload 4
    //   26: iconst_0
    //   27: invokevirtual 41	android/content/Context:openFileOutput	(Ljava/lang/String;I)Ljava/io/FileOutputStream;
    //   30: astore 7
    //   32: invokestatic 47	android/util/Xml:newSerializer	()Lorg/xmlpull/v1/XmlSerializer;
    //   35: astore 8
    //   37: aload 8
    //   39: aload 7
    //   41: aconst_null
    //   42: invokeinterface 53 3 0
    //   47: aload 8
    //   49: ldc 55
    //   51: iconst_1
    //   52: invokestatic 61	java/lang/Boolean:valueOf	(Z)Ljava/lang/Boolean;
    //   55: invokeinterface 65 3 0
    //   60: aload 8
    //   62: aconst_null
    //   63: ldc 67
    //   65: invokeinterface 71 3 0
    //   70: pop
    //   71: aload_3
    //   72: invokeinterface 75 1 0
    //   77: istore 25
    //   79: iload_2
    //   80: iload 25
    //   82: if_icmpge +130 -> 212
    //   85: aload_3
    //   86: iconst_0
    //   87: invokeinterface 79 2 0
    //   92: checkcast 81	android/support/v7/internal/widget/p
    //   95: astore 26
    //   97: aload 8
    //   99: aconst_null
    //   100: ldc 83
    //   102: invokeinterface 71 3 0
    //   107: pop
    //   108: aload 8
    //   110: aconst_null
    //   111: ldc 85
    //   113: aload 26
    //   115: getfield 88	android/support/v7/internal/widget/p:a	Landroid/content/ComponentName;
    //   118: invokevirtual 94	android/content/ComponentName:flattenToString	()Ljava/lang/String;
    //   121: invokeinterface 98 4 0
    //   126: pop
    //   127: aload 8
    //   129: aconst_null
    //   130: ldc 100
    //   132: aload 26
    //   134: getfield 104	android/support/v7/internal/widget/p:b	J
    //   137: invokestatic 107	java/lang/String:valueOf	(J)Ljava/lang/String;
    //   140: invokeinterface 98 4 0
    //   145: pop
    //   146: aload 8
    //   148: aconst_null
    //   149: ldc 109
    //   151: aload 26
    //   153: getfield 113	android/support/v7/internal/widget/p:c	F
    //   156: invokestatic 116	java/lang/String:valueOf	(F)Ljava/lang/String;
    //   159: invokeinterface 98 4 0
    //   164: pop
    //   165: aload 8
    //   167: aconst_null
    //   168: ldc 83
    //   170: invokeinterface 119 3 0
    //   175: pop
    //   176: iinc 2 1
    //   179: goto -100 -> 79
    //   182: astore 5
    //   184: invokestatic 122	android/support/v7/internal/widget/l:d	()Ljava/lang/String;
    //   187: new 124	java/lang/StringBuilder
    //   190: dup
    //   191: ldc 126
    //   193: invokespecial 129	java/lang/StringBuilder:<init>	(Ljava/lang/String;)V
    //   196: aload 4
    //   198: invokevirtual 133	java/lang/StringBuilder:append	(Ljava/lang/String;)Ljava/lang/StringBuilder;
    //   201: invokevirtual 136	java/lang/StringBuilder:toString	()Ljava/lang/String;
    //   204: aload 5
    //   206: invokestatic 142	android/util/Log:e	(Ljava/lang/String;Ljava/lang/String;Ljava/lang/Throwable;)I
    //   209: pop
    //   210: aconst_null
    //   211: areturn
    //   212: aload 8
    //   214: aconst_null
    //   215: ldc 67
    //   217: invokeinterface 119 3 0
    //   222: pop
    //   223: aload 8
    //   225: invokeinterface 145 1 0
    //   230: aload_0
    //   231: getfield 11	android/support/v7/internal/widget/q:a	Landroid/support/v7/internal/widget/l;
    //   234: iconst_1
    //   235: invokestatic 148	android/support/v7/internal/widget/l:a	(Landroid/support/v7/internal/widget/l;Z)Z
    //   238: pop
    //   239: aload 7
    //   241: ifnull -31 -> 210
    //   244: aload 7
    //   246: invokevirtual 153	java/io/FileOutputStream:close	()V
    //   249: aconst_null
    //   250: areturn
    //   251: astore 34
    //   253: aconst_null
    //   254: areturn
    //   255: astore 20
    //   257: invokestatic 122	android/support/v7/internal/widget/l:d	()Ljava/lang/String;
    //   260: new 124	java/lang/StringBuilder
    //   263: dup
    //   264: ldc 126
    //   266: invokespecial 129	java/lang/StringBuilder:<init>	(Ljava/lang/String;)V
    //   269: aload_0
    //   270: getfield 11	android/support/v7/internal/widget/q:a	Landroid/support/v7/internal/widget/l;
    //   273: invokestatic 156	android/support/v7/internal/widget/l:b	(Landroid/support/v7/internal/widget/l;)Ljava/lang/String;
    //   276: invokevirtual 133	java/lang/StringBuilder:append	(Ljava/lang/String;)Ljava/lang/StringBuilder;
    //   279: invokevirtual 136	java/lang/StringBuilder:toString	()Ljava/lang/String;
    //   282: aload 20
    //   284: invokestatic 142	android/util/Log:e	(Ljava/lang/String;Ljava/lang/String;Ljava/lang/Throwable;)I
    //   287: pop
    //   288: aload_0
    //   289: getfield 11	android/support/v7/internal/widget/q:a	Landroid/support/v7/internal/widget/l;
    //   292: iconst_1
    //   293: invokestatic 148	android/support/v7/internal/widget/l:a	(Landroid/support/v7/internal/widget/l;Z)Z
    //   296: pop
    //   297: aload 7
    //   299: ifnull -89 -> 210
    //   302: aload 7
    //   304: invokevirtual 153	java/io/FileOutputStream:close	()V
    //   307: aconst_null
    //   308: areturn
    //   309: astore 23
    //   311: aconst_null
    //   312: areturn
    //   313: astore 16
    //   315: invokestatic 122	android/support/v7/internal/widget/l:d	()Ljava/lang/String;
    //   318: new 124	java/lang/StringBuilder
    //   321: dup
    //   322: ldc 126
    //   324: invokespecial 129	java/lang/StringBuilder:<init>	(Ljava/lang/String;)V
    //   327: aload_0
    //   328: getfield 11	android/support/v7/internal/widget/q:a	Landroid/support/v7/internal/widget/l;
    //   331: invokestatic 156	android/support/v7/internal/widget/l:b	(Landroid/support/v7/internal/widget/l;)Ljava/lang/String;
    //   334: invokevirtual 133	java/lang/StringBuilder:append	(Ljava/lang/String;)Ljava/lang/StringBuilder;
    //   337: invokevirtual 136	java/lang/StringBuilder:toString	()Ljava/lang/String;
    //   340: aload 16
    //   342: invokestatic 142	android/util/Log:e	(Ljava/lang/String;Ljava/lang/String;Ljava/lang/Throwable;)I
    //   345: pop
    //   346: aload_0
    //   347: getfield 11	android/support/v7/internal/widget/q:a	Landroid/support/v7/internal/widget/l;
    //   350: iconst_1
    //   351: invokestatic 148	android/support/v7/internal/widget/l:a	(Landroid/support/v7/internal/widget/l;Z)Z
    //   354: pop
    //   355: aload 7
    //   357: ifnull -147 -> 210
    //   360: aload 7
    //   362: invokevirtual 153	java/io/FileOutputStream:close	()V
    //   365: aconst_null
    //   366: areturn
    //   367: astore 19
    //   369: aconst_null
    //   370: areturn
    //   371: astore 12
    //   373: invokestatic 122	android/support/v7/internal/widget/l:d	()Ljava/lang/String;
    //   376: new 124	java/lang/StringBuilder
    //   379: dup
    //   380: ldc 126
    //   382: invokespecial 129	java/lang/StringBuilder:<init>	(Ljava/lang/String;)V
    //   385: aload_0
    //   386: getfield 11	android/support/v7/internal/widget/q:a	Landroid/support/v7/internal/widget/l;
    //   389: invokestatic 156	android/support/v7/internal/widget/l:b	(Landroid/support/v7/internal/widget/l;)Ljava/lang/String;
    //   392: invokevirtual 133	java/lang/StringBuilder:append	(Ljava/lang/String;)Ljava/lang/StringBuilder;
    //   395: invokevirtual 136	java/lang/StringBuilder:toString	()Ljava/lang/String;
    //   398: aload 12
    //   400: invokestatic 142	android/util/Log:e	(Ljava/lang/String;Ljava/lang/String;Ljava/lang/Throwable;)I
    //   403: pop
    //   404: aload_0
    //   405: getfield 11	android/support/v7/internal/widget/q:a	Landroid/support/v7/internal/widget/l;
    //   408: iconst_1
    //   409: invokestatic 148	android/support/v7/internal/widget/l:a	(Landroid/support/v7/internal/widget/l;Z)Z
    //   412: pop
    //   413: aload 7
    //   415: ifnull -205 -> 210
    //   418: aload 7
    //   420: invokevirtual 153	java/io/FileOutputStream:close	()V
    //   423: aconst_null
    //   424: areturn
    //   425: astore 15
    //   427: aconst_null
    //   428: areturn
    //   429: astore 9
    //   431: aload_0
    //   432: getfield 11	android/support/v7/internal/widget/q:a	Landroid/support/v7/internal/widget/l;
    //   435: iconst_1
    //   436: invokestatic 148	android/support/v7/internal/widget/l:a	(Landroid/support/v7/internal/widget/l;Z)Z
    //   439: pop
    //   440: aload 7
    //   442: ifnull +8 -> 450
    //   445: aload 7
    //   447: invokevirtual 153	java/io/FileOutputStream:close	()V
    //   450: aload 9
    //   452: athrow
    //   453: astore 11
    //   455: goto -5 -> 450
    //
    // Exception table:
    //   from	to	target	type
    //   17	32	182	java/io/FileNotFoundException
    //   244	249	251	java/io/IOException
    //   37	79	255	java/lang/IllegalArgumentException
    //   85	176	255	java/lang/IllegalArgumentException
    //   212	230	255	java/lang/IllegalArgumentException
    //   302	307	309	java/io/IOException
    //   37	79	313	java/lang/IllegalStateException
    //   85	176	313	java/lang/IllegalStateException
    //   212	230	313	java/lang/IllegalStateException
    //   360	365	367	java/io/IOException
    //   37	79	371	java/io/IOException
    //   85	176	371	java/io/IOException
    //   212	230	371	java/io/IOException
    //   418	423	425	java/io/IOException
    //   37	79	429	finally
    //   85	176	429	finally
    //   212	230	429	finally
    //   257	288	429	finally
    //   315	346	429	finally
    //   373	404	429	finally
    //   445	450	453	java/io/IOException
  }
}

/* Location:           E:\Progs\Dev\Android\Decompile\apktool\zssq\zssq-dex2jar.jar
 * Qualified Name:     android.support.v7.internal.widget.q
 * JD-Core Version:    0.6.0
 */