package com.alipay.sdk.g;

final class c
  implements Runnable
{
  c(a parama)
  {
  }

  // ERROR //
  public final void run()
  {
    // Byte code:
    //   0: aload_0
    //   1: getfield 12	com/alipay/sdk/g/c:a	Lcom/alipay/sdk/g/a;
    //   4: getfield 24	com/alipay/sdk/g/a:b	Landroid/app/ProgressDialog;
    //   7: ifnull +23 -> 30
    //   10: aload_0
    //   11: getfield 12	com/alipay/sdk/g/c:a	Lcom/alipay/sdk/g/a;
    //   14: invokevirtual 27	com/alipay/sdk/g/a:a	()Z
    //   17: ifeq +13 -> 30
    //   20: aload_0
    //   21: getfield 12	com/alipay/sdk/g/c:a	Lcom/alipay/sdk/g/a;
    //   24: getfield 24	com/alipay/sdk/g/a:b	Landroid/app/ProgressDialog;
    //   27: invokevirtual 32	android/app/ProgressDialog:dismiss	()V
    //   30: aload_0
    //   31: getfield 12	com/alipay/sdk/g/c:a	Lcom/alipay/sdk/g/a;
    //   34: aconst_null
    //   35: putfield 24	com/alipay/sdk/g/a:b	Landroid/app/ProgressDialog;
    //   38: return
    //   39: astore_2
    //   40: aload_0
    //   41: getfield 12	com/alipay/sdk/g/c:a	Lcom/alipay/sdk/g/a;
    //   44: aconst_null
    //   45: putfield 24	com/alipay/sdk/g/a:b	Landroid/app/ProgressDialog;
    //   48: return
    //   49: astore_1
    //   50: aload_0
    //   51: getfield 12	com/alipay/sdk/g/c:a	Lcom/alipay/sdk/g/a;
    //   54: aconst_null
    //   55: putfield 24	com/alipay/sdk/g/a:b	Landroid/app/ProgressDialog;
    //   58: aload_1
    //   59: athrow
    //
    // Exception table:
    //   from	to	target	type
    //   0	30	39	java/lang/Exception
    //   0	30	49	finally
  }
}

/* Location:           E:\Progs\Dev\Android\Decompile\apktool\zssq\zssq-dex2jar.jar
 * Qualified Name:     com.alipay.sdk.g.c
 * JD-Core Version:    0.6.0
 */