package com.qq.e.comm.managers.plugin;

import com.qq.e.comm.net.NetworkCallBack;
import com.qq.e.comm.util.GDTLogger;

final class PM$a
  implements NetworkCallBack
{
  private String a;

  public PM$a(PM paramPM, String paramString)
  {
    this.a = paramString;
  }

  public final void onException(Exception paramException)
  {
    GDTLogger.report("Exception while update plugin", paramException);
  }

  // ERROR //
  public final void onResponse(com.qq.e.comm.net.rr.Request paramRequest, com.qq.e.comm.net.rr.Response paramResponse)
  {
    // Byte code:
    //   0: iconst_1
    //   1: istore_3
    //   2: aload_2
    //   3: invokeinterface 41 1 0
    //   8: sipush 200
    //   11: if_icmpne +444 -> 455
    //   14: ldc 43
    //   16: invokestatic 49	java/security/MessageDigest:getInstance	(Ljava/lang/String;)Ljava/security/MessageDigest;
    //   19: astore 10
    //   21: aload_2
    //   22: invokeinterface 53 1 0
    //   27: astore 11
    //   29: aload 11
    //   31: astore 5
    //   33: aload_0
    //   34: getfield 14	com/qq/e/comm/managers/plugin/PM$a:b	Lcom/qq/e/comm/managers/plugin/PM;
    //   37: invokestatic 58	com/qq/e/comm/managers/plugin/PM:a	(Lcom/qq/e/comm/managers/plugin/PM;)Ljava/io/File;
    //   40: astore 12
    //   42: new 60	java/io/FileOutputStream
    //   45: dup
    //   46: aload 12
    //   48: invokespecial 63	java/io/FileOutputStream:<init>	(Ljava/io/File;)V
    //   51: astore 8
    //   53: sipush 1024
    //   56: newarray byte
    //   58: astore 13
    //   60: aload 5
    //   62: aload 13
    //   64: invokevirtual 69	java/io/InputStream:read	([B)I
    //   67: istore 14
    //   69: iload 14
    //   71: ifle +50 -> 121
    //   74: aload 10
    //   76: aload 13
    //   78: iconst_0
    //   79: iload 14
    //   81: invokevirtual 73	java/security/MessageDigest:update	([BII)V
    //   84: aload 8
    //   86: aload 13
    //   88: iconst_0
    //   89: iload 14
    //   91: invokevirtual 76	java/io/FileOutputStream:write	([BII)V
    //   94: goto -34 -> 60
    //   97: astore 4
    //   99: aload 8
    //   101: astore 6
    //   103: ldc 78
    //   105: aload 4
    //   107: invokestatic 29	com/qq/e/comm/util/GDTLogger:report	(Ljava/lang/String;Ljava/lang/Throwable;)V
    //   110: aload 5
    //   112: invokestatic 84	com/qq/e/comm/util/FileUtil:tryClose	(Ljava/io/InputStream;)V
    //   115: aload 6
    //   117: invokestatic 87	com/qq/e/comm/util/FileUtil:tryClose	(Ljava/io/OutputStream;)V
    //   120: return
    //   121: aload 5
    //   123: invokestatic 84	com/qq/e/comm/util/FileUtil:tryClose	(Ljava/io/InputStream;)V
    //   126: aload 8
    //   128: invokestatic 87	com/qq/e/comm/util/FileUtil:tryClose	(Ljava/io/OutputStream;)V
    //   131: aload 10
    //   133: invokevirtual 91	java/security/MessageDigest:digest	()[B
    //   136: invokestatic 97	com/qq/e/comm/util/Md5Util:byteArrayToHexString	([B)Ljava/lang/String;
    //   139: astore 15
    //   141: invokestatic 102	com/qq/e/comm/util/a:a	()Lcom/qq/e/comm/util/a;
    //   144: aload_0
    //   145: getfield 19	com/qq/e/comm/managers/plugin/PM$a:a	Ljava/lang/String;
    //   148: aload 15
    //   150: invokevirtual 105	com/qq/e/comm/util/a:b	(Ljava/lang/String;Ljava/lang/String;)Z
    //   153: ifeq +222 -> 375
    //   156: aload_0
    //   157: getfield 14	com/qq/e/comm/managers/plugin/PM$a:b	Lcom/qq/e/comm/managers/plugin/PM;
    //   160: invokestatic 107	com/qq/e/comm/managers/plugin/PM:b	(Lcom/qq/e/comm/managers/plugin/PM;)Ljava/io/File;
    //   163: astore 18
    //   165: aload_1
    //   166: invokeinterface 113 1 0
    //   171: astore 19
    //   173: ldc 115
    //   175: astore 20
    //   177: invokestatic 118	com/qq/e/comm/managers/plugin/PM:a	()Ljava/util/regex/Pattern;
    //   180: aload 19
    //   182: invokevirtual 124	java/util/regex/Pattern:matcher	(Ljava/lang/CharSequence;)Ljava/util/regex/Matcher;
    //   185: astore 21
    //   187: aload 21
    //   189: invokevirtual 130	java/util/regex/Matcher:matches	()Z
    //   192: ifeq +11 -> 203
    //   195: aload 21
    //   197: iconst_1
    //   198: invokevirtual 134	java/util/regex/Matcher:group	(I)Ljava/lang/String;
    //   201: astore 20
    //   203: aload 20
    //   205: iconst_0
    //   206: invokestatic 140	com/qq/e/comm/util/StringUtil:parseInteger	(Ljava/lang/String;I)I
    //   209: istore 22
    //   211: iload 22
    //   213: sipush 504
    //   216: if_icmpge +39 -> 255
    //   219: new 142	java/lang/StringBuilder
    //   222: dup
    //   223: ldc 144
    //   225: invokespecial 147	java/lang/StringBuilder:<init>	(Ljava/lang/String;)V
    //   228: iload 22
    //   230: invokevirtual 151	java/lang/StringBuilder:append	(I)Ljava/lang/StringBuilder;
    //   233: ldc 153
    //   235: invokevirtual 156	java/lang/StringBuilder:append	(Ljava/lang/String;)Ljava/lang/StringBuilder;
    //   238: invokevirtual 159	java/lang/StringBuilder:toString	()Ljava/lang/String;
    //   241: invokestatic 162	com/qq/e/comm/util/GDTLogger:w	(Ljava/lang/String;)V
    //   244: aload 5
    //   246: invokestatic 84	com/qq/e/comm/util/FileUtil:tryClose	(Ljava/io/InputStream;)V
    //   249: aload 8
    //   251: invokestatic 87	com/qq/e/comm/util/FileUtil:tryClose	(Ljava/io/OutputStream;)V
    //   254: return
    //   255: new 142	java/lang/StringBuilder
    //   258: dup
    //   259: invokespecial 163	java/lang/StringBuilder:<init>	()V
    //   262: aload 20
    //   264: invokevirtual 156	java/lang/StringBuilder:append	(Ljava/lang/String;)Ljava/lang/StringBuilder;
    //   267: ldc 165
    //   269: invokevirtual 156	java/lang/StringBuilder:append	(Ljava/lang/String;)Ljava/lang/StringBuilder;
    //   272: aload_0
    //   273: getfield 19	com/qq/e/comm/managers/plugin/PM$a:a	Ljava/lang/String;
    //   276: invokevirtual 156	java/lang/StringBuilder:append	(Ljava/lang/String;)Ljava/lang/StringBuilder;
    //   279: invokevirtual 159	java/lang/StringBuilder:toString	()Ljava/lang/String;
    //   282: aload 18
    //   284: invokestatic 169	com/qq/e/comm/util/StringUtil:writeTo	(Ljava/lang/String;Ljava/io/File;)V
    //   287: aload 12
    //   289: aload_0
    //   290: getfield 14	com/qq/e/comm/managers/plugin/PM$a:b	Lcom/qq/e/comm/managers/plugin/PM;
    //   293: invokestatic 172	com/qq/e/comm/managers/plugin/PM:c	(Lcom/qq/e/comm/managers/plugin/PM;)Ljava/io/File;
    //   296: invokestatic 176	com/qq/e/comm/util/FileUtil:renameTo	(Ljava/io/File;Ljava/io/File;)Z
    //   299: ifeq +71 -> 370
    //   302: aload 18
    //   304: aload_0
    //   305: getfield 14	com/qq/e/comm/managers/plugin/PM$a:b	Lcom/qq/e/comm/managers/plugin/PM;
    //   308: invokestatic 179	com/qq/e/comm/managers/plugin/PM:d	(Lcom/qq/e/comm/managers/plugin/PM;)Ljava/io/File;
    //   311: invokestatic 176	com/qq/e/comm/util/FileUtil:renameTo	(Ljava/io/File;Ljava/io/File;)Z
    //   314: ifeq +56 -> 370
    //   317: new 142	java/lang/StringBuilder
    //   320: dup
    //   321: ldc 181
    //   323: invokespecial 147	java/lang/StringBuilder:<init>	(Ljava/lang/String;)V
    //   326: invokestatic 187	java/lang/System:currentTimeMillis	()J
    //   329: invokevirtual 190	java/lang/StringBuilder:append	(J)Ljava/lang/StringBuilder;
    //   332: ldc 192
    //   334: invokevirtual 156	java/lang/StringBuilder:append	(Ljava/lang/String;)Ljava/lang/StringBuilder;
    //   337: aload_0
    //   338: getfield 19	com/qq/e/comm/managers/plugin/PM$a:a	Ljava/lang/String;
    //   341: invokevirtual 156	java/lang/StringBuilder:append	(Ljava/lang/String;)Ljava/lang/StringBuilder;
    //   344: invokevirtual 159	java/lang/StringBuilder:toString	()Ljava/lang/String;
    //   347: invokestatic 194	com/qq/e/comm/util/GDTLogger:d	(Ljava/lang/String;)V
    //   350: iload_3
    //   351: ifne +8 -> 359
    //   354: ldc 196
    //   356: invokestatic 198	com/qq/e/comm/util/GDTLogger:report	(Ljava/lang/String;)V
    //   359: aload 5
    //   361: invokestatic 84	com/qq/e/comm/util/FileUtil:tryClose	(Ljava/io/InputStream;)V
    //   364: aload 8
    //   366: invokestatic 87	com/qq/e/comm/util/FileUtil:tryClose	(Ljava/io/OutputStream;)V
    //   369: return
    //   370: iconst_0
    //   371: istore_3
    //   372: goto -55 -> 317
    //   375: aload 12
    //   377: invokevirtual 203	java/io/File:delete	()Z
    //   380: pop
    //   381: iconst_2
    //   382: anewarray 4	java/lang/Object
    //   385: astore 17
    //   387: aload 17
    //   389: iconst_0
    //   390: aload_0
    //   391: getfield 19	com/qq/e/comm/managers/plugin/PM$a:a	Ljava/lang/String;
    //   394: aastore
    //   395: aload 17
    //   397: iconst_1
    //   398: aload 15
    //   400: aastore
    //   401: ldc 205
    //   403: aload 17
    //   405: invokestatic 211	java/lang/String:format	(Ljava/lang/String;[Ljava/lang/Object;)Ljava/lang/String;
    //   408: invokestatic 198	com/qq/e/comm/util/GDTLogger:report	(Ljava/lang/String;)V
    //   411: goto -52 -> 359
    //   414: astore 9
    //   416: ldc 213
    //   418: aload 9
    //   420: invokestatic 29	com/qq/e/comm/util/GDTLogger:report	(Ljava/lang/String;Ljava/lang/Throwable;)V
    //   423: aload 5
    //   425: invokestatic 84	com/qq/e/comm/util/FileUtil:tryClose	(Ljava/io/InputStream;)V
    //   428: aload 8
    //   430: invokestatic 87	com/qq/e/comm/util/FileUtil:tryClose	(Ljava/io/OutputStream;)V
    //   433: return
    //   434: astore 7
    //   436: aconst_null
    //   437: astore 5
    //   439: aconst_null
    //   440: astore 8
    //   442: aload 5
    //   444: invokestatic 84	com/qq/e/comm/util/FileUtil:tryClose	(Ljava/io/InputStream;)V
    //   447: aload 8
    //   449: invokestatic 87	com/qq/e/comm/util/FileUtil:tryClose	(Ljava/io/OutputStream;)V
    //   452: aload 7
    //   454: athrow
    //   455: new 142	java/lang/StringBuilder
    //   458: dup
    //   459: ldc 215
    //   461: invokespecial 147	java/lang/StringBuilder:<init>	(Ljava/lang/String;)V
    //   464: aload_2
    //   465: invokeinterface 41 1 0
    //   470: invokevirtual 151	java/lang/StringBuilder:append	(I)Ljava/lang/StringBuilder;
    //   473: invokevirtual 159	java/lang/StringBuilder:toString	()Ljava/lang/String;
    //   476: invokestatic 198	com/qq/e/comm/util/GDTLogger:report	(Ljava/lang/String;)V
    //   479: return
    //   480: astore 7
    //   482: aconst_null
    //   483: astore 8
    //   485: goto -43 -> 442
    //   488: astore 7
    //   490: goto -48 -> 442
    //   493: astore 7
    //   495: aload 6
    //   497: astore 8
    //   499: goto -57 -> 442
    //   502: astore 9
    //   504: aconst_null
    //   505: astore 5
    //   507: aconst_null
    //   508: astore 8
    //   510: goto -94 -> 416
    //   513: astore 9
    //   515: aconst_null
    //   516: astore 8
    //   518: goto -102 -> 416
    //   521: astore 4
    //   523: aconst_null
    //   524: astore 5
    //   526: aconst_null
    //   527: astore 6
    //   529: goto -426 -> 103
    //   532: astore 4
    //   534: aconst_null
    //   535: astore 6
    //   537: goto -434 -> 103
    //
    // Exception table:
    //   from	to	target	type
    //   53	60	97	java/io/IOException
    //   60	69	97	java/io/IOException
    //   74	94	97	java/io/IOException
    //   121	173	97	java/io/IOException
    //   177	203	97	java/io/IOException
    //   203	211	97	java/io/IOException
    //   219	244	97	java/io/IOException
    //   255	317	97	java/io/IOException
    //   317	350	97	java/io/IOException
    //   354	359	97	java/io/IOException
    //   375	411	97	java/io/IOException
    //   53	60	414	java/security/NoSuchAlgorithmException
    //   60	69	414	java/security/NoSuchAlgorithmException
    //   74	94	414	java/security/NoSuchAlgorithmException
    //   121	173	414	java/security/NoSuchAlgorithmException
    //   177	203	414	java/security/NoSuchAlgorithmException
    //   203	211	414	java/security/NoSuchAlgorithmException
    //   219	244	414	java/security/NoSuchAlgorithmException
    //   255	317	414	java/security/NoSuchAlgorithmException
    //   317	350	414	java/security/NoSuchAlgorithmException
    //   354	359	414	java/security/NoSuchAlgorithmException
    //   375	411	414	java/security/NoSuchAlgorithmException
    //   14	29	434	finally
    //   33	53	480	finally
    //   53	60	488	finally
    //   60	69	488	finally
    //   74	94	488	finally
    //   121	173	488	finally
    //   177	203	488	finally
    //   203	211	488	finally
    //   219	244	488	finally
    //   255	317	488	finally
    //   317	350	488	finally
    //   354	359	488	finally
    //   375	411	488	finally
    //   416	423	488	finally
    //   103	110	493	finally
    //   14	29	502	java/security/NoSuchAlgorithmException
    //   33	53	513	java/security/NoSuchAlgorithmException
    //   14	29	521	java/io/IOException
    //   33	53	532	java/io/IOException
  }
}

/* Location:           E:\Progs\Dev\Android\Decompile\apktool\zssq\zssq-dex2jar.jar
 * Qualified Name:     com.qq.e.comm.managers.plugin.PM.a
 * JD-Core Version:    0.6.0
 */